bd_scan_yocto/BBClass.py
bd_scan_yocto/BOMClass.py
bd_scan_yocto/ComponentClass.py
bd_scan_yocto/ComponentListClass.py
bd_scan_yocto/ConfigClass.py
bd_scan_yocto/OEClass.py
bd_scan_yocto/RecipeClass.py
bd_scan_yocto/RecipeListClass.py
bd_scan_yocto/SBOMClass.py
bd_scan_yocto/VulnClass.py
bd_scan_yocto/VulnListClass.py
bd_scan_yocto/__init__.py
bd_scan_yocto/main.py
bd_scan_yocto_via_sbom-1.2.5.dist-info/licenses/LICENSE
bd_scan_yocto_via_sbom-1.2.5.dist-info/METADATA
bd_scan_yocto_via_sbom-1.2.5.dist-info/WHEEL
bd_scan_yocto_via_sbom-1.2.5.dist-info/entry_points.txt
bd_scan_yocto_via_sbom-1.2.5.dist-info/top_level.txt
bd_scan_yocto_via_sbom-1.2.5.dist-info/RECORD
