Metadata-Version: 2.4
Name: bd_scan_yocto_via_sbom
Version: 1.2.5
Summary: BD_yocto_import_sbom - BD Script to import a Yocto project to Black Duck SCA by scanning license.manifest and creating an SBOM file
Author-email: Matthew Brady <mbrad@blackduck.com>
Project-URL: Homepage, https://github.com/blackducksoftware/bd_scan_yocto_via_sbom
Project-URL: Issues, https://github.com/blackducksoftware/bd_scan_yocto_via_sbom/issues
Classifier: Programming Language :: Python :: 3
Classifier: License :: OSI Approved :: MIT License
Classifier: Operating System :: OS Independent
Requires-Python: >=3.8
License-File: LICENSE
Requires-Dist: blackduck>=1.1.3
Requires-Dist: bd-kernel-vulns
Requires-Dist: requests
Requires-Dist: semver
Requires-Dist: aiohttp
Dynamic: license-file
